{"commitInfo":{"timestamp":1673843449069,"operation":"WRITE","operationParameters":{"mode":"Overwrite","partitionBy":"[\"job\"]"},"isolationLevel":"Serializable","isBlindAppend":false,"operationMetrics":{"numFiles":"12","numOutputRows":"4521","numOutputBytes":"123970"},"engineInfo":"Apache-Spark/3.3.1 Delta-Lake/2.2.0","txnId":"5b0511ac-3de4-42b7-9095-cb468a72e8aa"}}
{"protocol":{"minReaderVersion":1,"minWriterVersion":2}}
{"metaData":{"id":"2be85f4e-1213-45f7-ba08-193905097479","format":{"provider":"parquet","options":{}},"schemaString":"{\"type\":\"struct\",\"fields\":[{\"name\":\"age\",\"type\":\"string\",\"nullable\":true,\"metadata\":{}},{\"name\":\"job\",\"type\":\"string\",\"nullable\":true,\"metadata\":{}},{\"name\":\"marital\",\"type\":\"string\",\"nullable\":true,\"metadata\":{}},{\"name\":\"education\",\"type\":\"string\",\"nullable\":true,\"metadata\":{}},{\"name\":\"default\",\"type\":\"string\",\"nullable\":true,\"metadata\":{}},{\"name\":\"balance\",\"type\":\"string\",\"nullable\":true,\"metadata\":{}},{\"name\":\"housing\",\"type\":\"string\",\"nullable\":true,\"metadata\":{}},{\"name\":\"loan\",\"type\":\"string\",\"nullable\":true,\"metadata\":{}},{\"name\":\"contact\",\"type\":\"string\",\"nullable\":true,\"metadata\":{}},{\"name\":\"day\",\"type\":\"string\",\"nullable\":true,\"metadata\":{}},{\"name\":\"month\",\"type\":\"string\",\"nullable\":true,\"metadata\":{}},{\"name\":\"duration\",\"type\":\"string\",\"nullable\":true,\"metadata\":{}},{\"name\":\"campaign\",\"type\":\"string\",\"nullable\":true,\"metadata\":{}},{\"name\":\"pdays\",\"type\":\"string\",\"nullable\":true,\"metadata\":{}},{\"name\":\"previous\",\"type\":\"string\",\"nullable\":true,\"metadata\":{}},{\"name\":\"poutcome\",\"type\":\"string\",\"nullable\":true,\"metadata\":{}},{\"name\":\"y\",\"type\":\"string\",\"nullable\":true,\"metadata\":{}}]}","partitionColumns":["job"],"configuration":{},"createdTime":1673843440904}}
{"add":{"path":"job=admin./part-00000-d27bb89d-e319-4f36-9507-14fd6d07cfe9.c000.snappy.parquet","partitionValues":{"job":"admin."},"size":11789,"modificationTime":1673843444878,"dataChange":true,"stats":"{\"numRecords\":478,\"minValues\":{\"age\":\"22\",\"marital\":\"divorced\",\"education\":\"primary\",\"default\":\"no\",\"balance\":\"-1\",\"housing\":\"no\",\"loan\":\"no\",\"contact\":\"cellular\",\"day\":\"1\",\"month\":\"apr\",\"duration\":\"10\",\"campaign\":\"1\",\"pdays\":\"-1\",\"previous\":\"0\",\"poutcome\":\"failure\",\"y\":\"no\"},\"maxValues\":{\"age\":\"66\",\"marital\":\"single\",\"education\":\"unknown\",\"default\":\"yes\",\"balance\":\"998\",\"housing\":\"yes\",\"loan\":\"yes\",\"contact\":\"unknown\",\"day\":\"9\",\"month\":\"sep\",\"duration\":\"99\",\"campaign\":\"9\",\"pdays\":\"99\",\"previous\":\"9\",\"poutcome\":\"unknown\",\"y\":\"yes\"},\"nullCount\":{\"age\":0,\"marital\":0,\"education\":0,\"default\":0,\"balance\":0,\"housing\":0,\"loan\":0,\"contact\":0,\"day\":0,\"month\":0,\"duration\":0,\"campaign\":0,\"pdays\":0,\"previous\":0,\"poutcome\":0,\"y\":0}}"}}
{"add":{"path":"job=blue-collar/part-00000-323cc29c-7e80-4f83-94f6-e5943179dd0e.c000.snappy.parquet","partitionValues":{"job":"blue-collar"},"size":18076,"modificationTime":1673843445252,"dataChange":true,"stats":"{\"numRecords\":946,\"minValues\":{\"age\":\"23\",\"marital\":\"divorced\",\"education\":\"primary\",\"default\":\"no\",\"balance\":\"-1\",\"housing\":\"no\",\"loan\":\"no\",\"contact\":\"cellular\",\"day\":\"1\",\"month\":\"apr\",\"duration\":\"10\",\"campaign\":\"1\",\"pdays\":\"-1\",\"previous\":\"0\",\"poutcome\":\"failure\",\"y\":\"no\"},\"maxValues\":{\"age\":\"75\",\"marital\":\"single\",\"education\":\"unknown\",\"default\":\"yes\",\"balance\":\"999\",\"housing\":\"yes\",\"loan\":\"yes\",\"contact\":\"unknown\",\"day\":\"9\",\"month\":\"sep\",\"duration\":\"998\",\"campaign\":\"9\",\"pdays\":\"99\",\"previous\":\"9\",\"poutcome\":\"unknown\",\"y\":\"yes\"},\"nullCount\":{\"age\":0,\"marital\":0,\"education\":0,\"default\":0,\"balance\":0,\"housing\":0,\"loan\":0,\"contact\":0,\"day\":0,\"month\":0,\"duration\":0,\"campaign\":0,\"pdays\":0,\"previous\":0,\"poutcome\":0,\"y\":0}}"}}
{"add":{"path":"job=entrepreneur/part-00000-2698d168-c48d-422f-8e09-ffc17338b234.c000.snappy.parquet","partitionValues":{"job":"entrepreneur"},"size":7389,"modificationTime":1673843445373,"dataChange":true,"stats":"{\"numRecords\":168,\"minValues\":{\"age\":\"23\",\"marital\":\"divorced\",\"education\":\"primary\",\"default\":\"no\",\"balance\":\"-118\",\"housing\":\"no\",\"loan\":\"no\",\"contact\":\"cellular\",\"day\":\"1\",\"month\":\"apr\",\"duration\":\"10\",\"campaign\":\"1\",\"pdays\":\"-1\",\"previous\":\"0\",\"poutcome\":\"failure\",\"y\":\"no\"},\"maxValues\":{\"age\":\"63\",\"marital\":\"single\",\"education\":\"unknown\",\"default\":\"yes\",\"balance\":\"98\",\"housing\":\"yes\",\"loan\":\"yes\",\"contact\":\"unknown\",\"day\":\"9\",\"month\":\"sep\",\"duration\":\"988\",\"campaign\":\"8\",\"pdays\":\"414\",\"previous\":\"8\",\"poutcome\":\"unknown\",\"y\":\"yes\"},\"nullCount\":{\"age\":0,\"marital\":0,\"education\":0,\"default\":0,\"balance\":0,\"housing\":0,\"loan\":0,\"contact\":0,\"day\":0,\"month\":0,\"duration\":0,\"campaign\":0,\"pdays\":0,\"previous\":0,\"poutcome\":0,\"y\":0}}"}}
{"add":{"path":"job=housemaid/part-00000-1ec0ab6d-95f8-42d3-9a4e-60c71dbb144b.c000.snappy.parquet","partitionValues":{"job":"housemaid"},"size":6685,"modificationTime":1673843445573,"dataChange":true,"stats":"{\"numRecords\":112,\"minValues\":{\"age\":\"26\",\"marital\":\"divorced\",\"education\":\"primary\",\"default\":\"no\",\"balance\":\"-278\",\"housing\":\"no\",\"loan\":\"no\",\"contact\":\"cellular\",\"day\":\"10\",\"month\":\"apr\",\"duration\":\"107\",\"campaign\":\"1\",\"pdays\":\"-1\",\"previous\":\"0\",\"poutcome\":\"failure\",\"y\":\"no\"},\"maxValues\":{\"age\":\"80\",\"marital\":\"single\",\"education\":\"unknown\",\"default\":\"yes\",\"balance\":\"976\",\"housing\":\"yes\",\"loan\":\"yes\",\"contact\":\"unknown\",\"day\":\"9\",\"month\":\"sep\",\"duration\":\"993\",\"campaign\":\"8\",\"pdays\":\"99\",\"previous\":\"5\",\"poutcome\":\"unknown\",\"y\":\"yes\"},\"nullCount\":{\"age\":0,\"marital\":0,\"education\":0,\"default\":0,\"balance\":0,\"housing\":0,\"loan\":0,\"contact\":0,\"day\":0,\"month\":0,\"duration\":0,\"campaign\":0,\"pdays\":0,\"previous\":0,\"poutcome\":0,\"y\":0}}"}}
{"add":{"path":"job=management/part-00000-bec8cb94-f5dc-4b2f-b2f2-9c9d0b8bd167.c000.snappy.parquet","partitionValues":{"job":"management"},"size":18650,"modificationTime":1673843445696,"dataChange":true,"stats":"{\"numRecords\":969,\"minValues\":{\"age\":\"23\",\"marital\":\"divorced\",\"education\":\"primary\",\"default\":\"no\",\"balance\":\"-105\",\"housing\":\"no\",\"loan\":\"no\",\"contact\":\"cellular\",\"day\":\"1\",\"month\":\"apr\",\"duration\":\"10\",\"campaign\":\"1\",\"pdays\":\"-1\",\"previous\":\"0\",\"poutcome\":\"failure\",\"y\":\"no\"},\"maxValues\":{\"age\":\"80\",\"marital\":\"single\",\"education\":\"unknown\",\"default\":\"yes\",\"balance\":\"998\",\"housing\":\"yes\",\"loan\":\"yes\",\"contact\":\"unknown\",\"day\":\"9\",\"month\":\"sep\",\"duration\":\"998\",\"campaign\":\"9\",\"pdays\":\"99\",\"previous\":\"9\",\"poutcome\":\"unknown\",\"y\":\"yes\"},\"nullCount\":{\"age\":0,\"marital\":0,\"education\":0,\"default\":0,\"balance\":0,\"housing\":0,\"loan\":0,\"contact\":0,\"day\":0,\"month\":0,\"duration\":0,\"campaign\":0,\"pdays\":0,\"previous\":0,\"poutcome\":0,\"y\":0}}"}}
{"add":{"path":"job=retired/part-00000-7eb8c7dd-da36-45f5-bf55-c154c3cc683c.c000.snappy.parquet","partitionValues":{"job":"retired"},"size":8576,"modificationTime":1673843445824,"dataChange":true,"stats":"{\"numRecords\":230,\"minValues\":{\"age\":\"24\",\"marital\":\"divorced\",\"education\":\"primary\",\"default\":\"no\",\"balance\":\"-1\",\"housing\":\"no\",\"loan\":\"no\",\"contact\":\"cellular\",\"day\":\"1\",\"month\":\"apr\",\"duration\":\"100\",\"campaign\":\"1\",\"pdays\":\"-1\",\"previous\":\"0\",\"poutcome\":\"failure\",\"y\":\"no\"},\"maxValues\":{\"age\":\"87\",\"marital\":\"single\",\"education\":\"unknown\",\"default\":\"yes\",\"balance\":\"9976\",\"housing\":\"yes\",\"loan\":\"yes\",\"contact\":\"unknown\",\"day\":\"9\",\"month\":\"sep\",\"duration\":\"97\",\"campaign\":\"9\",\"pdays\":\"94\",\"previous\":\"9\",\"poutcome\":\"unknown\",\"y\":\"yes\"},\"nullCount\":{\"age\":0,\"marital\":0,\"education\":0,\"default\":0,\"balance\":0,\"housing\":0,\"loan\":0,\"contact\":0,\"day\":0,\"month\":0,\"duration\":0,\"campaign\":0,\"pdays\":0,\"previous\":0,\"poutcome\":0,\"y\":0}}"}}
{"add":{"path":"job=self-employed/part-00000-90e18151-0457-4de8-a64c-499509ff7d0a.c000.snappy.parquet","partitionValues":{"job":"self-employed"},"size":7694,"modificationTime":1673843445903,"dataChange":true,"stats":"{\"numRecords\":183,\"minValues\":{\"age\":\"25\",\"marital\":\"divorced\",\"education\":\"primary\",\"default\":\"no\",\"balance\":\"-196\",\"housing\":\"no\",\"loan\":\"no\",\"contact\":\"cellular\",\"day\":\"10\",\"month\":\"apr\",\"duration\":\"101\",\"campaign\":\"1\",\"pdays\":\"-1\",\"previous\":\"0\",\"poutcome\":\"failure\",\"y\":\"no\"},\"maxValues\":{\"age\":\"62\",\"marital\":\"single\",\"education\":\"unknown\",\"default\":\"yes\",\"balance\":\"980\",\"housing\":\"yes\",\"loan\":\"yes\",\"contact\":\"unknown\",\"day\":\"9\",\"month\":\"sep\",\"duration\":\"97\",\"campaign\":\"8\",\"pdays\":\"96\",\"previous\":\"8\",\"poutcome\":\"unknown\",\"y\":\"yes\"},\"nullCount\":{\"age\":0,\"marital\":0,\"education\":0,\"default\":0,\"balance\":0,\"housing\":0,\"loan\":0,\"contact\":0,\"day\":0,\"month\":0,\"duration\":0,\"campaign\":0,\"pdays\":0,\"previous\":0,\"poutcome\":0,\"y\":0}}"}}
{"add":{"path":"job=services/part-00000-9c92279f-f0d6-42b1-bdf7-f8214d726a38.c000.snappy.parquet","partitionValues":{"job":"services"},"size":10869,"modificationTime":1673843446023,"dataChange":true,"stats":"{\"numRecords\":417,\"minValues\":{\"age\":\"21\",\"marital\":\"divorced\",\"education\":\"primary\",\"default\":\"no\",\"balance\":\"-1\",\"housing\":\"no\",\"loan\":\"no\",\"contact\":\"cellular\",\"day\":\"1\",\"month\":\"apr\",\"duration\":\"10\",\"campaign\":\"1\",\"pdays\":\"-1\",\"previous\":\"0\",\"poutcome\":\"failure\",\"y\":\"no\"},\"maxValues\":{\"age\":\"60\",\"marital\":\"single\",\"education\":\"unknown\",\"default\":\"yes\",\"balance\":\"991\",\"housing\":\"yes\",\"loan\":\"yes\",\"contact\":\"unknown\",\"day\":\"9\",\"month\":\"oct\",\"duration\":\"994\",\"campaign\":\"9\",\"pdays\":\"97\",\"previous\":\"9\",\"poutcome\":\"unknown\",\"y\":\"yes\"},\"nullCount\":{\"age\":0,\"marital\":0,\"education\":0,\"default\":0,\"balance\":0,\"housing\":0,\"loan\":0,\"contact\":0,\"day\":0,\"month\":0,\"duration\":0,\"campaign\":0,\"pdays\":0,\"previous\":0,\"poutcome\":0,\"y\":0}}"}}
{"add":{"path":"job=student/part-00000-5a0e7181-14f7-414c-86c5-9fc634cc33c1.c000.snappy.parquet","partitionValues":{"job":"student"},"size":6201,"modificationTime":1673843446106,"dataChange":true,"stats":"{\"numRecords\":84,\"minValues\":{\"age\":\"19\",\"marital\":\"married\",\"education\":\"primary\",\"default\":\"no\",\"balance\":\"-147\",\"housing\":\"no\",\"loan\":\"no\",\"contact\":\"cellular\",\"day\":\"10\",\"month\":\"apr\",\"duration\":\"101\",\"campaign\":\"1\",\"pdays\":\"-1\",\"previous\":\"0\",\"poutcome\":\"failure\",\"y\":\"no\"},\"maxValues\":{\"age\":\"42\",\"marital\":\"single\",\"education\":\"unknown\",\"default\":\"yes\",\"balance\":\"9216\",\"housing\":\"yes\",\"loan\":\"yes\",\"contact\":\"unknown\",\"day\":\"9\",\"month\":\"sep\",\"duration\":\"95\",\"campaign\":\"9\",\"pdays\":\"98\",\"previous\":\"8\",\"poutcome\":\"unknown\",\"y\":\"yes\"},\"nullCount\":{\"age\":0,\"marital\":0,\"education\":0,\"default\":0,\"balance\":0,\"housing\":0,\"loan\":0,\"contact\":0,\"day\":0,\"month\":0,\"duration\":0,\"campaign\":0,\"pdays\":0,\"previous\":0,\"poutcome\":0,\"y\":0}}"}}
{"add":{"path":"job=technician/part-00000-7037ca3e-4f4d-414c-a702-781e70654864.c000.snappy.parquet","partitionValues":{"job":"technician"},"size":15791,"modificationTime":1673843446233,"dataChange":true,"stats":"{\"numRecords\":768,\"minValues\":{\"age\":\"22\",\"marital\":\"divorced\",\"education\":\"primary\",\"default\":\"no\",\"balance\":\"-1053\",\"housing\":\"no\",\"loan\":\"no\",\"contact\":\"cellular\",\"day\":\"1\",\"month\":\"apr\",\"duration\":\"10\",\"campaign\":\"1\",\"pdays\":\"-1\",\"previous\":\"0\",\"poutcome\":\"failure\",\"y\":\"no\"},\"maxValues\":{\"age\":\"71\",\"marital\":\"single\",\"education\":\"unknown\",\"default\":\"yes\",\"balance\":\"999\",\"housing\":\"yes\",\"loan\":\"yes\",\"contact\":\"unknown\",\"day\":\"9\",\"month\":\"sep\",\"duration\":\"990\",\"campaign\":\"9\",\"pdays\":\"96\",\"previous\":\"9\",\"poutcome\":\"unknown\",\"y\":\"yes\"},\"nullCount\":{\"age\":0,\"marital\":0,\"education\":0,\"default\":0,\"balance\":0,\"housing\":0,\"loan\":0,\"contact\":0,\"day\":0,\"month\":0,\"duration\":0,\"campaign\":0,\"pdays\":0,\"previous\":0,\"poutcome\":0,\"y\":0}}"}}
{"add":{"path":"job=unemployed/part-00000-312335ce-c11e-48e2-9339-a6fd06fcdc6f.c000.snappy.parquet","partitionValues":{"job":"unemployed"},"size":6886,"modificationTime":1673843446317,"dataChange":true,"stats":"{\"numRecords\":128,\"minValues\":{\"age\":\"24\",\"marital\":\"divorced\",\"education\":\"primary\",\"default\":\"no\",\"balance\":\"-110\",\"housing\":\"no\",\"loan\":\"no\",\"contact\":\"cellular\",\"day\":\"1\",\"month\":\"apr\",\"duration\":\"100\",\"campaign\":\"1\",\"pdays\":\"-1\",\"previous\":\"0\",\"poutcome\":\"failure\",\"y\":\"no\"},\"maxValues\":{\"age\":\"60\",\"marital\":\"single\",\"education\":\"unknown\",\"default\":\"yes\",\"balance\":\"991\",\"housing\":\"yes\",\"loan\":\"yes\",\"contact\":\"unknown\",\"day\":\"9\",\"month\":\"sep\",\"duration\":\"97\",\"campaign\":\"8\",\"pdays\":\"95\",\"previous\":\"7\",\"poutcome\":\"unknown\",\"y\":\"yes\"},\"nullCount\":{\"age\":0,\"marital\":0,\"education\":0,\"default\":0,\"balance\":0,\"housing\":0,\"loan\":0,\"contact\":0,\"day\":0,\"month\":0,\"duration\":0,\"campaign\":0,\"pdays\":0,\"previous\":0,\"poutcome\":0,\"y\":0}}"}}
{"add":{"path":"job=unknown/part-00000-cf7249d1-af5a-4bfb-9d13-eaf6e834f536.c000.snappy.parquet","partitionValues":{"job":"unknown"},"size":5364,"modificationTime":1673843446498,"dataChange":true,"stats":"{\"numRecords\":38,\"minValues\":{\"age\":\"27\",\"marital\":\"divorced\",\"education\":\"primary\",\"default\":\"no\",\"balance\":\"0\",\"housing\":\"no\",\"loan\":\"no\",\"contact\":\"cellular\",\"day\":\"1\",\"month\":\"apr\",\"duration\":\"104\",\"campaign\":\"1\",\"pdays\":\"-1\",\"previous\":\"0\",\"poutcome\":\"failure\",\"y\":\"no\"},\"maxValues\":{\"age\":\"71\",\"marital\":\"single\",\"education\":\"unknown\",\"default\":\"no\",\"balance\":\"914\",\"housing\":\"yes\",\"loan\":\"yes\",\"contact\":\"unknown\",\"day\":\"9\",\"month\":\"sep\",\"duration\":\"98\",\"campaign\":\"9\",\"pdays\":\"99\",\"previous\":\"6\",\"poutcome\":\"unknown\",\"y\":\"yes\"},\"nullCount\":{\"age\":0,\"marital\":0,\"education\":0,\"default\":0,\"balance\":0,\"housing\":0,\"loan\":0,\"contact\":0,\"day\":0,\"month\":0,\"duration\":0,\"campaign\":0,\"pdays\":0,\"previous\":0,\"poutcome\":0,\"y\":0}}"}}
